escale/__init__.py
escale/__main__.py
escale/base/__init__.py
escale/base/config.py
escale/base/essential.py
escale/base/exceptions.py
escale/base/launcher.py
escale/base/ssl.py
escale/base/subprocess.py
escale/base/timer.py
escale/cli/__init__.py
escale/cli/auth.py
escale/cli/controller.py
escale/cli/ctl.py
escale/cli/format.py
escale/cli/license.py
escale/cli/config/__init__.py
escale/cli/config/amazoncloud.py
escale/cli/config/b2.py
escale/cli/config/config.py
escale/cli/config/dropbox.py
escale/cli/config/google.py
escale/cli/config/googlecloud.py
escale/cli/config/googledrive.py
escale/cli/config/hubic.py
escale/cli/config/onedrive.py
escale/cli/config/rclone.py
escale/cli/config/s3.py
escale/cli/config/sftp.py
escale/cli/config/swift.py
escale/cli/config/yandex.py
escale/encryption/__init__.py
escale/encryption/encryption.py
escale/encryption/fernet.py
escale/log/__init__.py
escale/log/log.py
escale/log/socket.py
escale/manager/__init__.py
escale/manager/access.py
escale/manager/backup.py
escale/manager/cache.py
escale/manager/config.py
escale/manager/history.py
escale/manager/index.py
escale/manager/manager.py
escale/manager/migration.py
escale/oauth/__init__.py
escale/relay/__init__.py
escale/relay/ftp.py
escale/relay/index.py
escale/relay/info.py
escale/relay/localmount.py
escale/relay/relay.py
escale/relay/ssh.py
escale/relay/generic/__init__.py
escale/relay/generic/rclone.py
escale/relay/google/__init__.py
escale/relay/google/drive.py
escale/relay/webdav/__init__.py
escale/relay/webdav/client.py
escale/relay/webdav/webdav.py
escale-0.7.11.data/scripts/escale
escale-0.7.11.data/scripts/escalectl
syncacre/__init__.py
syncacre/__main__.py
escale-0.7.11.dist-info/LICENSE
escale-0.7.11.dist-info/LICENSE_CeCILL-C
escale-0.7.11.dist-info/LICENSE_easywebdav
escale-0.7.11.dist-info/LICENSE_syncacre
escale-0.7.11.dist-info/METADATA
escale-0.7.11.dist-info/WHEEL
escale-0.7.11.dist-info/top_level.txt
escale-0.7.11.dist-info/RECORD
