Metadata-Version: 2.1
Name: escale
Version: 0.7.11
Summary: Escale - Client-to-client synchronization based on external relay storage
Home-page: https://github.com/francoislaurent/escale
Author: François Laurent
Author-email: francois.laurent1@protonmail.com
License: CeCILL-C
Platform: UNKNOWN
Classifier: License :: OSI Approved :: CEA CNRS Inria Logiciel Libre License, version 2.1 (CeCILL-2.1)
Classifier: Environment :: No Input/Output (Daemon)
Classifier: Intended Audience :: End Users/Desktop
Classifier: Intended Audience :: Science/Research
Classifier: Operating System :: MacOS :: MacOS X
Classifier: Operating System :: POSIX :: Linux
Classifier: Operating System :: Unix
Classifier: Topic :: Communications :: File Sharing
Classifier: Programming Language :: Python :: 2
Classifier: Programming Language :: Python :: 2.7
Classifier: Programming Language :: Python :: 3
Classifier: Programming Language :: Python :: 3.5
Classifier: Programming Language :: Python :: 3.6
Requires-Dist: python-daemon
Requires-Dist: requests
Provides-Extra: blowfish
Requires-Dist: cryptography ; extra == 'blowfish'
Provides-Extra: fernet
Requires-Dist: cryptography ; extra == 'fernet'
Provides-Extra: webdav
Requires-Dist: pyopenssl ; extra == 'webdav'
Requires-Dist: requests ; extra == 'webdav'
